liquimigrate-0.6.0.dist-info/pbr.json
liquimigrate-0.6.0.dist-info/DESCRIPTION.rst
liquimigrate-0.6.0.dist-info/WHEEL
liquimigrate-0.6.0.dist-info/top_level.txt
liquimigrate-0.6.0.dist-info/RECORD
liquimigrate-0.6.0.dist-info/metadata.json
liquimigrate-0.6.0.dist-info/METADATA
liquimigrate/__init__.py
liquimigrate/models.py
liquimigrate/url.py
liquimigrate/views.py
liquimigrate/settings.py
liquimigrate/vendor/liquibase.jar
liquimigrate/vendor/LICENSE.txt
liquimigrate/vendor/lib/snakeyaml-1.13.jar
liquimigrate/vendor/connectors/postgresql-jdbc3-8.2.jar
liquimigrate/vendor/connectors/mysql-connector-java-5.0.8-bin.jar
liquimigrate/management/__init__.py
liquimigrate/management/commands/migrate.py
liquimigrate/management/commands/__init__.py
liquimigrate/management/commands/syncdb.py
liquimigrate/management/commands/makemigrations.py
liquimigrate/management/commands/squashmigrations.py
liquimigrate/management/commands/liquibase.py
