Metadata-Version: 2.0
Name: liquimigrate
Version: 0.6.0
Summary: Liquibase migrations with django
Home-page: https://github.com/onjin/liquimigrate
Author: Marek Wywiał
Author-email: onjinx@gmail.com
License: BSD
Keywords: liquimigrate liquibase django
Platform: UNKNOWN
Classifier: Development Status :: 5 - Production/Stable
Classifier: Intended Audience :: Developers
Classifier: License :: OSI Approved :: BSD License
Classifier: Natural Language :: English
Classifier: Programming Language :: Python :: 2
Classifier: Programming Language :: Python :: 2.6
Classifier: Programming Language :: Python :: 2.7
Classifier: Programming Language :: Python :: 3
Classifier: Programming Language :: Python :: 3.3
Classifier: Programming Language :: Python :: 3.4
